decode/__init__.py
decode/assign.py
decode/convert.py
decode/correct.py
decode/fit.py
decode/load.py
decode/make.py
decode/plot.py
decode/py.typed
decode/qlook.py
decode/select.py
decode/stats.py
decode/utils.py
decode/data/alma_atm.txt
decode-2025.10.0.dist-info/METADATA
decode-2025.10.0.dist-info/WHEEL
decode-2025.10.0.dist-info/entry_points.txt
decode-2025.10.0.dist-info/licenses/LICENSE
decode-2025.10.0.dist-info/RECORD
