Metadata-Version: 2.4
Name: decode
Version: 2025.10.0
Summary: DESHIMA code for data analysis
Project-URL: homepage, https://deshima-dev.github.io/decode
Project-URL: repository, https://github.com/deshima-dev/decode
Author-email: Akio Taniguchi <taniguchi.akio@gmail.com>, Juri Yamanaka <j.yamanaka@a.phys.nagoya-u.ac.jp>, Shinji Fujita <s-fujita@ism.ac.jp>
License: MIT License
License-File: LICENSE
Keywords: astronomy,data-analysis,deshima,spectroscopy,submillimeter
Classifier: License :: OSI Approved :: MIT License
Classifier: Programming Language :: Python :: 3
Classifier: Programming Language :: Python :: 3.9
Classifier: Programming Language :: Python :: 3.10
Classifier: Programming Language :: Python :: 3.11
Classifier: Programming Language :: Python :: 3.12
Requires-Python: <3.13,>=3.9
Requires-Dist: astropy<8,>=6
Requires-Dist: dask<2026,>=2024
Requires-Dist: dems<2026.0,>=2025.6
Requires-Dist: fire<1.0,>=0.5
Requires-Dist: matplotlib<4,>=3
Requires-Dist: ndtools<2,>=1
Requires-Dist: numpy<3.0,>=1.23
Requires-Dist: pandas-stubs<3,>=2
Requires-Dist: pandas<3,>=2
Requires-Dist: scikit-learn<2,>=1
Requires-Dist: scipy<2,>=1
Requires-Dist: tomli-w<2,>=1
Requires-Dist: xarray<2026,>=2024
Requires-Dist: zarr<3,>=2
